{
  "name": "Radiochemotherapy_Detailed",
  "remarks": [
    "A blank module"
  ],
  "states": {
    "Initial": {
      "type": "Initial",
      "direct_transition": "Encounter_Chemo_1_Week_Before",
      "name": "Initial"
    },
    "Terminal": {
      "type": "Terminal",
      "name": "Terminal"
    },
    "Day_Counter": {
      "type": "SetAttribute",
      "attribute": "day_radiochemo",
      "direct_transition": "Week_Counter_2",
      "value": 1,
      "name": "Day_Counter"
    },
    "Radiotherapy": {
      "type": "Procedure",
      "codes": [
        {
          "system": "SNOMED-CT",
          "code": 428416002,
          "display": "Radiotherapy to neck (procedure)",
          "value_set": ""
        }
      ],
      "distribution": {
        "kind": "UNIFORM",
        "parameters": {
          "high": 15,
          "low": 5
        }
      },
      "unit": "minutes",
      "direct_transition": "Chemo_Therapeutics",
      "name": "Radiotherapy"
    },
    "Increase_Day": {
      "type": "Counter",
      "attribute": "day_radiochemo",
      "action": "increment",
      "direct_transition": "Delay_1_Day",
      "name": "Increase_Day"
    },
    "Increase_Week": {
      "type": "Counter",
      "attribute": "week_radiochemo",
      "action": "increment",
      "direct_transition": "Day_Counter_2",
      "name": "Increase_Week"
    },
    "End_Therapy": {
      "type": "Simple",
      "conditional_transition": [
        {
          "transition": "Terminal",
          "condition": {
            "condition_type": "Attribute",
            "attribute": "week_radiochemo",
            "operator": ">",
            "value": 7
          }
        },
        {
          "transition": "Therapy"
        }
      ],
      "name": "End_Therapy"
    },
    "Delay_1_Day": {
      "type": "Delay",
      "distribution": {
        "kind": "EXACT",
        "parameters": {
          "value": 1
        }
      },
      "unit": "days",
      "direct_transition": "End_Therapy",
      "name": "Delay_1_Day"
    },
    "Increase_Counter": {
      "type": "Simple",
      "conditional_transition": [
        {
          "transition": "Increase_Week",
          "condition": {
            "condition_type": "Attribute",
            "attribute": "day_radiochemo",
            "operator": "==",
            "value": 7
          }
        },
        {
          "transition": "Increase_Day"
        }
      ],
      "name": "Increase_Counter"
    },
    "Day_Counter_2": {
      "type": "SetAttribute",
      "attribute": "day_radiochemo",
      "value": 1,
      "direct_transition": "Delay_1_Day",
      "name": "Day_Counter_2"
    },
    "Week_Counter_2": {
      "type": "SetAttribute",
      "attribute": "week_radiochemo",
      "value": 1,
      "direct_transition": "Therapy",
      "name": "Week_Counter_2"
    },
    "Therapy": {
      "type": "Simple",
      "conditional_transition": [
        {
          "transition": "Encounter_Therapy",
          "condition": {
            "condition_type": "Attribute",
            "attribute": "day_radiochemo",
            "operator": "<",
            "value": 6
          }
        },
        {
          "transition": "Increase_Counter"
        }
      ],
      "name": "Therapy"
    },
    "1_Week_Delay": {
      "type": "Delay",
      "distribution": {
        "kind": "EXACT",
        "parameters": {
          "value": 1
        }
      },
      "unit": "weeks",
      "direct_transition": "Day_Counter",
      "name": "1_Week_Delay"
    },
    "Chemo_Therapeutics": {
      "type": "Simple",
      "conditional_transition": [
        {
          "transition": "Cisplatin_And_Cetuximab",
          "condition": {
            "condition_type": "Attribute",
            "attribute": "day_radiochemo",
            "operator": "==",
            "value": 1
          }
        },
        {
          "transition": "EndEncounter_Therapy"
        }
      ],
      "name": "Chemo_Therapeutics"
    },
    "Encounter_Therapy": {
      "type": "Encounter",
      "encounter_class": "ambulatory",
      "telemedicine_possibility": "none",
      "codes": [
        {
          "system": "SNOMED-CT",
          "code": 185345009,
          "display": "Encounter for symptom",
          "value_set": ""
        }
      ],
      "direct_transition": "Radiotherapy",
      "name": "Encounter_Therapy"
    },
    "Cetuximab_1_Week_Before": {
      "type": "MedicationOrder",
      "codes": [
        {
          "system": "RxNorm",
          "code": 318341,
          "display": "400mg Cetuximab",
          "value_set": ""
        }
      ],
      "direct_transition": "Simultaneously_Chemotherapy_Procedure",
      "administration": true,
      "assign_to_attribute": "radioChemoMedL1",
      "name": "Cetuximab_1_Week_Before"
    },
    "Simultaneously_Chemotherapy_Procedure": {
      "type": "Procedure",
      "codes": [
        {
          "system": "SNOMED-CT",
          "code": 367336001,
          "display": "Chemotherapy (procedure)",
          "value_set": ""
        }
      ],
      "duration": {
        "low": 0,
        "high": 2,
        "unit": "hours"
      },
      "direct_transition": "End_Current_Simultaneously_Chemo_Medication",
      "name": "Simultaneously_Chemotherapy_Procedure"
    },
    "End_Current_Simultaneously_Chemo_Medication": {
      "type": "MedicationEnd",
      "referenced_by_attribute": "radioChemoMedL1",
      "direct_transition": "EndEncounter_Chemo_1_Week_Before",
      "name": "End_Current_Simultaneously_Chemo_Medication"
    },
    "Cisplatin_And_Cetuximab": {
      "type": "MedicationOrder",
      "codes": [
        {
          "system": "RxNorm",
          "code": 1736853,
          "display": "40 mg/m^2 Cisplatin Injection",
          "value_set": ""
        },
        {
          "system": "RxNorm",
          "code": 318341,
          "display": "250 mg/m^2 Cetuximab",
          "value_set": ""
        }
      ],
      "direct_transition": "Simultaneously_Chemotherapy_Procedure_2",
      "assign_to_attribute": "radioChemoMedL2",
      "name": "Cisplatin_And_Cetuximab"
    },
    "Simultaneously_Chemotherapy_Procedure_2": {
      "type": "Procedure",
      "codes": [
        {
          "system": "SNOMED-CT",
          "code": 367336001,
          "display": "Chemotherapy (procedure)",
          "value_set": ""
        }
      ],
      "duration": {
        "low": 0,
        "high": 2,
        "unit": "hours"
      },
      "direct_transition": "End_Current_Simultaneously_Chemo_Medication_2",
      "name": "Simultaneously_Chemotherapy_Procedure_2"
    },
    "End_Current_Simultaneously_Chemo_Medication_2": {
      "type": "MedicationEnd",
      "referenced_by_attribute": "radioChemoMedL2",
      "direct_transition": "EndEncounter_Therapy",
      "name": "End_Current_Simultaneously_Chemo_Medication_2"
    },
    "Encounter_Chemo_1_Week_Before": {
      "type": "Encounter",
      "encounter_class": "ambulatory",
      "telemedicine_possibility": "none",
      "codes": [
        {
          "system": "SNOMED-CT",
          "code": 185345009,
          "display": "Encounter for symptom",
          "value_set": ""
        }
      ],
      "direct_transition": "Cetuximab_1_Week_Before",
      "name": "Encounter_Chemo_1_Week_Before"
    },
    "EndEncounter_Therapy": {
      "type": "EncounterEnd",
      "direct_transition": "Increase_Counter",
      "name": "EndEncounter_Therapy"
    },
    "EndEncounter_Chemo_1_Week_Before": {
      "type": "EncounterEnd",
      "direct_transition": "1_Week_Delay",
      "name": "EndEncounter_Chemo_1_Week_Before"
    }
  },
  "gmf_version": 2
}